liudas_data_crowler/__init___.py
liudas_data_crowler/main.py
liudas_data_crowler-0.1.0.dist-info/METADATA
liudas_data_crowler-0.1.0.dist-info/WHEEL
liudas_data_crowler-0.1.0.dist-info/RECORD
